pydexcom/__init__.py
pydexcom/const.py
pydexcom/dexcom.py
pydexcom/errors.py
pydexcom/glucose_reading.py
pydexcom/py.typed
pydexcom/util.py
pydexcom-0.5.1.dist-info/METADATA
pydexcom-0.5.1.dist-info/WHEEL
pydexcom-0.5.1.dist-info/licenses/LICENSE
pydexcom-0.5.1.dist-info/RECORD
