Metadata-Version: 2.4
Name: pydexcom
Version: 0.5.1
Summary: Python API to interact with Dexcom Share API
Author: Gage Benne
License: MIT
License-File: LICENSE
Keywords: dexcom
Requires-Python: >=3.9
Requires-Dist: requests>=2.0
